README.md
setup.cfg
setup.py
playrandom/playrandom.py
playrandom.egg-info/PKG-INFO
playrandom.egg-info/SOURCES.txt
playrandom.egg-info/dependency_links.txt
playrandom.egg-info/entry_points.txt
playrandom.egg-info/requires.txt
playrandom.egg-info/top_level.txt