Metadata-Version: 1.1
Name: playrandom
Version: 0.0.1
Summary: command line tool to play random media from given folders
Home-page: https://github.com/terhorstd/playrandom
Author: Dennis Terhorst
Author-email: d.terhorst@fz-juelich.de
License: BSD
Platform: UNKNOWN
Classifier: Development Status :: 3 - Alpha
Classifier: Environment :: Console
Classifier: Intended Audience :: End Users/Desktop
Classifier: License :: OSI Approved :: BSD License
Classifier: Natural Language :: English
Classifier: Operating System :: OS Independent
Classifier: Programming Language :: Python :: 3
Classifier: Topic :: Multimedia :: Video
Classifier: Topic :: Multimedia :: Sound/Audio
